pbe/__init__.py
pbe/pbe.py
pbe/test.py
pbe/untitled0.py
pbe-0.0.2.dist-info/License.txt
pbe-0.0.2.dist-info/METADATA
pbe-0.0.2.dist-info/WHEEL
pbe-0.0.2.dist-info/top_level.txt
pbe-0.0.2.dist-info/RECORD
