Metadata-Version: 2.1
Name: pbe
Version: 0.0.2
Summary: Package to solve population balance equations (PBE) for aggregation processes using the *fixed pivot* method
Home-page: https://github.com/HugoMVale/pbe
Author: Hugo
License: UNKNOWN
Platform: UNKNOWN
Classifier: Programming Language :: Python :: 3
Classifier: License :: OSI Approved :: GNU General Public License v3 or later (GPLv3+)
Classifier: Operating System :: OS Independent
Requires-Python: >=3.6
